endless_pagination/__init__.py
endless_pagination/decorators.py
endless_pagination/exceptions.py
endless_pagination/loaders.py
endless_pagination/models.py
endless_pagination/paginators.py
endless_pagination/settings.py
endless_pagination/utils.py
endless_pagination/views.py
endless_pagination/locale/de/LC_MESSAGES/django.mo
endless_pagination/locale/de/LC_MESSAGES/django.po
endless_pagination/locale/es/LC_MESSAGES/django.mo
endless_pagination/locale/es/LC_MESSAGES/django.po
endless_pagination/locale/fr/LC_MESSAGES/django.mo
endless_pagination/locale/fr/LC_MESSAGES/django.po
endless_pagination/locale/it/LC_MESSAGES/django.mo
endless_pagination/locale/it/LC_MESSAGES/django.po
endless_pagination/locale/zh_CN/LC_MESSAGES/django.mo
endless_pagination/locale/zh_CN/LC_MESSAGES/django.po
endless_pagination/static/endless_pagination/js/endless-pagination.js
endless_pagination/static/endless_pagination/js/endless.js
endless_pagination/static/endless_pagination/js/endless_on_scroll.js
endless_pagination/templates/endless/current_link.html
endless_pagination/templates/endless/page_link.html
endless_pagination/templates/endless/show_more.html
endless_pagination/templates/endless/show_pages.html
endless_pagination/templatetags/endless.py
endless_pagination/tests/__init__.py
endless_pagination/tests/test_decorators.py
endless_pagination/tests/test_loaders.py
endless_pagination/tests/test_models.py
endless_pagination/tests/test_paginators.py
endless_pagination/tests/test_utils.py
endless_pagination/tests/test_views.py
endless_pagination/tests/integration/__init__.py
endless_pagination/tests/integration/test_callbacks.py
endless_pagination/tests/integration/test_chunks.py
endless_pagination/tests/integration/test_digg.py
endless_pagination/tests/integration/test_multiple.py
endless_pagination/tests/integration/test_onscroll.py
endless_pagination/tests/integration/test_twitter.py
endless_pagination/tests/templatetags/test_endless.py
webstack_django_endless_pagination-3.0.2.dist-info/METADATA
webstack_django_endless_pagination-3.0.2.dist-info/WHEEL
webstack_django_endless_pagination-3.0.2.dist-info/RECORD
