Metadata-Version: 2.3
Name: webstack-django-endless-pagination
Version: 3.0.2
Summary: Django Endless Pagination can be used to provide Twitter-style or Digg-style pagination
Project-URL: repository, http://github.com/webstack/django-endless-pagination.git
Author-email: Francesco Banconi <francesco.banconi@gmail.com>
Maintainer-email: Stéphane Raimbault <stephane.raimbault@webstack.fr>
License-Expression: MIT
Keywords: django,pagination
Classifier: Development Status :: 5 - Production/Stable
Classifier: Environment :: Web Environment
Classifier: Framework :: Django
Classifier: Intended Audience :: Developers
Classifier: License :: OSI Approved :: MIT License
Classifier: Programming Language :: Python
Classifier: Programming Language :: Python :: 3
Requires-Python: >=3.6
Requires-Dist: django<6.0,>=3.0
